./.gitignore
./PKG-INFO
./README.md
./py.typed
./pyproject.toml
./tests/test_ultralytics.py
./vision_agents/plugins/ultralytics/__init__.py
./vision_agents/plugins/ultralytics/yolo_pose_processor.py
vision_agents/plugins/ultralytics/__init__.py
vision_agents/plugins/ultralytics/yolo_pose_processor.py
vision_agents_plugins_ultralytics-0.2.10.dist-info/METADATA
vision_agents_plugins_ultralytics-0.2.10.dist-info/WHEEL
vision_agents_plugins_ultralytics-0.2.10.dist-info/RECORD
