Metadata-Version: 2.4
Name: vision-agents-plugins-ultralytics
Version: 0.2.10
Summary: Ultralytics YOLO plugin for GetStream
Project-URL: Documentation, https://visionagents.ai/
Project-URL: Website, https://visionagents.ai/
Project-URL: Source, https://github.com/GetStream/Vision-Agents
License-Expression: MIT
Requires-Python: >=3.10
Requires-Dist: numpy>=2.0.0
Requires-Dist: ultralytics>=8.3.206
Requires-Dist: vision-agents
